<?xml version="1.0" encoding="utf-8"?><ArrayOfCreatureValues xmlns:xsd="http://www.w3.org/2001/XMLSchema" xmlns:xsi="http://www.w3.org/2001/XMLSchema-instance"><CreatureValues><creatureType>Trekkin</creatureType><evolutionType>Mustrakk</evolutionType><damageType>Electric</damageType><bodyType>Pet</bodyType><levelToEvolve>40</levelToEvolve><evolution>1</evolution><damage>78</damage><speed>99</speed><defense>69</defense><magic>70</magic></CreatureValues><CreatureValues><creatureType>Padoru</creatureType><evolutionType>Passimus</evolutionType><damageType>Ghost</damageType><bodyType>Plant</bodyType><levelToEvolve>40</levelToEvolve><evolution>1</evolution><damage>70</damage><speed>80</speed><defense>60</defense><magic>90</magic></CreatureValues><CreatureValues><creatureType>Gaia</creatureType><evolutionType>None</evolutionType><damageType>Plant</damageType><bodyType>Pet</bodyType><levelToEvolve>-1</levelToEvolve><evolution>2</evolution><damage>80</damage><speed>55</speed><defense>90</defense><magic>75</magic></CreatureValues><CreatureValues><creatureType>Mub</creatureType><evolutionType>None</evolutionType><damageType>Psychic</damageType><bodyType>Water</bodyType><levelToEvolve>-1</levelToEvolve><evolution>1</evolution><damage>94</damage><speed>64</speed><defense>74</defense><magic>100</magic></CreatureValues><CreatureValues><creatureType>Buapi</creatureType><evolutionType>Carpide</evolutionType><damageType>Fire</damageType><bodyType>Ghost</bodyType><levelToEvolve>40</levelToEvolve><evolution>1</evolution><damage>70</damage><speed>75</speed><defense>65</defense><magic>90</magic></CreatureValues><CreatureValues><creatureType>Vex</creatureType><evolutionType>None</evolutionType><damageType>Psychic</damageType><bodyType>Onyx</bodyType><levelToEvolve>-1</levelToEvolve><evolution>2</evolution><damage>89</damage><speed>79</speed><defense>69</defense><magic>79</magic></CreatureValues><CreatureValues><creatureType>Goette</creatureType><evolutionType>None</evolutionType><damageType>Psychic</damageType><bodyType>Ghost</bodyType><levelToEvolve>-1</levelToEvolve><evolution>2</evolution><damage>40</damage><speed>80</speed><defense>80</defense><magic>100</magic></CreatureValues><CreatureValues><creatureType>Straia</creatureType><evolutionType>None</evolutionType><damageType>Electric</damageType><bodyType>Plant</bodyType><levelToEvolve>-1</levelToEvolve><evolution>1</evolution><damage>85</damage><speed>85</speed><defense>73</defense><magic>89</magic></CreatureValues><CreatureValues><creatureType>Chiro</creatureType><evolutionType>Machiron</evolutionType><damageType>Fire</damageType><bodyType>Onyx</bodyType><levelToEvolve>40</levelToEvolve><evolution>1</evolution><damage>90</damage><speed>68</speed><defense>68</defense><magic>90</magic></CreatureValues><CreatureValues><creatureType>Zelix</creatureType><evolutionType>None</evolutionType><damageType>Onyx</damageType><bodyType>Pet</bodyType><levelToEvolve>-1</levelToEvolve><evolution>1</evolution><damage>60</damage><speed>86</speed><defense>70</defense><magic>100</magic></CreatureValues><CreatureValues><creatureType>Ignim</creatureType><evolutionType>Volbrite</evolutionType><damageType>Fire</damageType><bodyType>Onyx</bodyType><levelToEvolve>40</levelToEvolve><evolution>1</evolution><damage>75</damage><speed>65</speed><defense>75</defense><magic>85</magic></CreatureValues><CreatureValues><creatureType>Volbrite</creatureType><evolutionType>Helion</evolutionType><damageType>Fire</damageType><bodyType>Onyx</bodyType><levelToEvolve>80</levelToEvolve><evolution>2</evolution><damage>75</damage><speed>65</speed><defense>75</defense><magic>85</magic></CreatureValues><CreatureValues><creatureType>Helion</creatureType><evolutionType>None</evolutionType><damageType>Fire</damageType><bodyType>Onyx</bodyType><levelToEvolve>-1</levelToEvolve><evolution>3</evolution><damage>75</damage><speed>65</speed><defense>75</defense><magic>85</magic></CreatureValues><CreatureValues><creatureType>Podmol</creatureType><evolutionType>Olangui</evolutionType><damageType>Psychic</damageType><bodyType>Water</bodyType><levelToEvolve>40</levelToEvolve><evolution>1</evolution><damage>80</damage><speed>80</speed><defense>75</defense><magic>65</magic></CreatureValues><CreatureValues><creatureType>Gravlus</creatureType><evolutionType>None</evolutionType><damageType>Sand</damageType><bodyType>Onyx</bodyType><levelToEvolve>-1</levelToEvolve><evolution>1</evolution><damage>80</damage><speed>70</speed><defense>90</defense><magic>60</magic></CreatureValues><CreatureValues><creatureType>Machiron</creatureType><evolutionType>None</evolutionType><damageType>Psychic</damageType><bodyType>Onyx</bodyType><levelToEvolve>-1</levelToEvolve><evolution>2</evolution><damage>90</damage><speed>68</speed><defense>68</defense><magic>90</magic></CreatureValues><CreatureValues><creatureType>Vyladium</creatureType><evolutionType>None</evolutionType><damageType>Plant</damageType><bodyType>Onyx</bodyType><levelToEvolve>-1</levelToEvolve><evolution>3</evolution><damage>70</damage><speed>70</speed><defense>100</defense><magic>60</magic></CreatureValues><CreatureValues><creatureType>Zoandi</creatureType><evolutionType>None</evolutionType><damageType>Ghost</damageType><bodyType>Water</bodyType><levelToEvolve>-1</levelToEvolve><evolution>1</evolution><damage>75</damage><speed>66</speed><defense>85</defense><magic>90</magic></CreatureValues><CreatureValues><creatureType>Minita</creatureType><evolutionType>Amusk</evolutionType><damageType>Plant</damageType><bodyType>Pet</bodyType><levelToEvolve>40</levelToEvolve><evolution>1</evolution><damage>70</damage><speed>80</speed><defense>70</defense><magic>80</magic></CreatureValues><CreatureValues><creatureType>Sungen</creatureType><evolutionType>None</evolutionType><damageType>Onyx</damageType><bodyType>Psychic</bodyType><levelToEvolve>-1</levelToEvolve><evolution>1</evolution><damage>500</damage><speed>500</speed><defense>500</defense><magic>500</magic></CreatureValues><CreatureValues><creatureType>Tephra</creatureType><evolutionType>None</evolutionType><damageType>Sand</damageType><bodyType>Fire</bodyType><levelToEvolve>-1</levelToEvolve><evolution>1</evolution><damage>85</damage><speed>50</speed><defense>85</defense><magic>80</magic></CreatureValues><CreatureValues><creatureType>Archor</creatureType><evolutionType>None</evolutionType><damageType>Onyx</damageType><bodyType>Water</bodyType><levelToEvolve>-1</levelToEvolve><evolution>2</evolution><damage>80</damage><speed>65</speed><defense>85</defense><magic>70</magic></CreatureValues><CreatureValues><creatureType>Eschiin</creatureType><evolutionType>Escheon</evolutionType><damageType>Water</damageType><bodyType>Plant</bodyType><levelToEvolve>40</levelToEvolve><evolution>1</evolution><damage>65</damage><speed>65</speed><defense>95</defense><magic>80</magic></CreatureValues><CreatureValues><creatureType>Thecoga</creatureType><evolutionType>None</evolutionType><damageType>Sand</damageType><bodyType>Pet</bodyType><levelToEvolve>-1</levelToEvolve><evolution>1</evolution><damage>85</damage><speed>75</speed><defense>70</defense><magic>70</magic></CreatureValues><CreatureValues><creatureType>Adamep</creatureType><evolutionType>Repitine</evolutionType><damageType>Electric</damageType><bodyType>Plant</bodyType><levelToEvolve>40</levelToEvolve><evolution>1</evolution><damage>70</damage><speed>85</speed><defense>65</defense><magic>80</magic></CreatureValues><CreatureValues><creatureType>Veryl</creatureType><evolutionType>Vyladium</evolutionType><damageType>Plant</damageType><bodyType>Onyx</bodyType><levelToEvolve>80</levelToEvolve><evolution>2</evolution><damage>70</damage><speed>70</speed><defense>100</defense><magic>60</magic></CreatureValues><CreatureValues><creatureType>Dratar</creatureType><evolutionType>None</evolutionType><damageType>Sand</damageType><bodyType>Fire</bodyType><levelToEvolve>-1</levelToEvolve><evolution>2</evolution><damage>80</damage><speed>70</speed><defense>80</defense><magic>70</magic></CreatureValues><CreatureValues><creatureType>Blotin</creatureType><evolutionType>Blossar</evolutionType><damageType>Onyx</damageType><bodyType>Plant</bodyType><levelToEvolve>40</levelToEvolve><evolution>1</evolution><damage>80</damage><speed>70</speed><defense>80</defense><magic>70</magic></CreatureValues><CreatureValues><creatureType>Tidae</creatureType><evolutionType>Strax</evolutionType><damageType>Water</damageType><bodyType>Water</bodyType><levelToEvolve>40</levelToEvolve><evolution>1</evolution><damage>72</damage><speed>100</speed><defense>72</defense><magic>72</magic></CreatureValues><CreatureValues><creatureType>Carpide</creatureType><evolutionType>Hospan</evolutionType><damageType>Fire</damageType><bodyType>Ghost</bodyType><levelToEvolve>80</levelToEvolve><evolution>2</evolution><damage>70</damage><speed>75</speed><defense>65</defense><magic>90</magic></CreatureValues><CreatureValues><creatureType>Derkom</creatureType><evolutionType>None</evolutionType><damageType>Sand</damageType><bodyType>Pet</bodyType><levelToEvolve>-1</levelToEvolve><evolution>2</evolution><damage>89</damage><speed>69</speed><defense>79</defense><magic>79</magic></CreatureValues><CreatureValues><creatureType>Gitt</creatureType><evolutionType>Goette</evolutionType><damageType>Psychic</damageType><bodyType>Ghost</bodyType><levelToEvolve>40</levelToEvolve><evolution>1</evolution><damage>40</damage><speed>80</speed><defense>80</defense><magic>100</magic></CreatureValues><CreatureValues><creatureType>Vanyr</creatureType><evolutionType>Veryl</evolutionType><damageType>Plant</damageType><bodyType>Onyx</bodyType><levelToEvolve>40</levelToEvolve><evolution>1</evolution><damage>70</damage><speed>70</speed><defense>100</defense><magic>60</magic></CreatureValues><CreatureValues><creatureType>Passimus</creatureType><evolutionType>Padonar</evolutionType><damageType>Ghost</damageType><bodyType>Plant</bodyType><levelToEvolve>80</levelToEvolve><evolution>2</evolution><damage>70</damage><speed>80</speed><defense>60</defense><magic>90</magic></CreatureValues><CreatureValues><creatureType>Gabip</creatureType><evolutionType>Gaia</evolutionType><damageType>Pet</damageType><bodyType>Pet</bodyType><levelToEvolve>40</levelToEvolve><evolution>1</evolution><damage>80</damage><speed>55</speed><defense>90</defense><magic>75</magic></CreatureValues><CreatureValues><creatureType>Mustrakk</creatureType><evolutionType>None</evolutionType><damageType>Electric</damageType><bodyType>Pet</bodyType><levelToEvolve>-1</levelToEvolve><evolution>2</evolution><damage>78</damage><speed>99</speed><defense>69</defense><magic>70</magic></CreatureValues><CreatureValues><creatureType>Olangui</creatureType><evolutionType>None</evolutionType><damageType>Psychic</damageType><bodyType>Water</bodyType><levelToEvolve>-1</levelToEvolve><evolution>2</evolution><damage>80</damage><speed>80</speed><defense>75</defense><magic>65</magic></CreatureValues><CreatureValues><creatureType>Edrak</creatureType><evolutionType>Derkom</evolutionType><damageType>Sand</damageType><bodyType>Pet</bodyType><levelToEvolve>40</levelToEvolve><evolution>1</evolution><damage>89</damage><speed>69</speed><defense>79</defense><magic>79</magic></CreatureValues><CreatureValues><creatureType>Amusk</creatureType><evolutionType>None</evolutionType><damageType>Plant</damageType><bodyType>Pet</bodyType><levelToEvolve>-1</levelToEvolve><evolution>2</evolution><damage>70</damage><speed>80</speed><defense>70</defense><magic>80</magic></CreatureValues><CreatureValues><creatureType>KinVex</creatureType><evolutionType>Vex</evolutionType><damageType>Psychic</damageType><bodyType>Onyx</bodyType><levelToEvolve>40</levelToEvolve><evolution>1</evolution><damage>89</damage><speed>79</speed><defense>69</defense><magic>79</magic></CreatureValues><CreatureValues><creatureType>Blossar</creatureType><evolutionType>None</evolutionType><damageType>Onyx</damageType><bodyType>Plant</bodyType><levelToEvolve>-1</levelToEvolve><evolution>2</evolution><damage>80</damage><speed>70</speed><defense>80</defense><magic>70</magic></CreatureValues><CreatureValues><creatureType>Tachi</creatureType><evolutionType>Dratar</evolutionType><damageType>Sand</damageType><bodyType>Fire</bodyType><levelToEvolve>40</levelToEvolve><evolution>1</evolution><damage>80</damage><speed>70</speed><defense>80</defense><magic>70</magic></CreatureValues><CreatureValues><creatureType>Repitine</creatureType><evolutionType>None</evolutionType><damageType>Electric</damageType><bodyType>Plant</bodyType><levelToEvolve>-1</levelToEvolve><evolution>2</evolution><damage>70</damage><speed>85</speed><defense>65</defense><magic>80</magic></CreatureValues><CreatureValues><creatureType>Nox</creatureType><evolutionType>None</evolutionType><damageType>Onyx</damageType><bodyType>Fire</bodyType><levelToEvolve>-1</levelToEvolve><evolution>2</evolution><damage>89</damage><speed>73</speed><defense>85</defense><magic>69</magic></CreatureValues><CreatureValues><creatureType>Hypollus</creatureType><evolutionType>None</evolutionType><damageType>Ghost</damageType><bodyType>Psychic</bodyType><levelToEvolve>-1</levelToEvolve><evolution>1</evolution><damage>90</damage><speed>66</speed><defense>75</defense><magic>85</magic></CreatureValues><CreatureValues><creatureType>Amaphila</creatureType><evolutionType>None</evolutionType><damageType>Sand</damageType><bodyType>Psychic</bodyType><levelToEvolve>-1</levelToEvolve><evolution>1</evolution><damage>88</damage><speed>80</speed><defense>68</defense><magic>80</magic></CreatureValues><CreatureValues><creatureType>Padonar</creatureType><evolutionType>None</evolutionType><damageType>Ghost</damageType><bodyType>Plant</bodyType><levelToEvolve>-1</levelToEvolve><evolution>3</evolution><damage>70</damage><speed>80</speed><defense>60</defense><magic>90</magic></CreatureValues><CreatureValues><creatureType>Hospan</creatureType><evolutionType>None</evolutionType><damageType>Fire</damageType><bodyType>Ghost</bodyType><levelToEvolve>-1</levelToEvolve><evolution>3</evolution><damage>70</damage><speed>75</speed><defense>65</defense><magic>90</magic></CreatureValues><CreatureValues><creatureType>Mirchin</creatureType><evolutionType>Archor</evolutionType><damageType>Onyx</damageType><bodyType>Water</bodyType><levelToEvolve>40</levelToEvolve><evolution>1</evolution><damage>80</damage><speed>65</speed><defense>85</defense><magic>70</magic></CreatureValues><CreatureValues><creatureType>Laspit</creatureType><evolutionType>Nox</evolutionType><damageType>Onyx</damageType><bodyType>Fire</bodyType><levelToEvolve>40</levelToEvolve><evolution>1</evolution><damage>89</damage><speed>73</speed><defense>85</defense><magic>69</magic></CreatureValues><CreatureValues><creatureType>Dreed</creatureType><evolutionType>None</evolutionType><damageType>Plant</damageType><bodyType>Plant</bodyType><levelToEvolve>-1</levelToEvolve><evolution>2</evolution><damage>75</damage><speed>75</speed><defense>80</defense><magic>70</magic></CreatureValues><CreatureValues><creatureType>Moley</creatureType><evolutionType>Ryclus</evolutionType><damageType>Water</damageType><bodyType>Water</bodyType><levelToEvolve>40</levelToEvolve><evolution>1</evolution><damage>80</damage><speed>80</speed><defense>70</defense><magic>70</magic></CreatureValues><CreatureValues><creatureType>Ryclus</creatureType><evolutionType>None</evolutionType><damageType>Water</damageType><bodyType>Water</bodyType><levelToEvolve>-1</levelToEvolve><evolution>2</evolution><damage>80</damage><speed>80</speed><defense>70</defense><magic>70</magic></CreatureValues><CreatureValues><creatureType>Tizi</creatureType><evolutionType>Laczat</evolutionType><damageType>Psychic</damageType><bodyType>Sand</bodyType><levelToEvolve>40</levelToEvolve><evolution>1</evolution><damage>70</damage><speed>70</speed><defense>75</defense><magic>85</magic></CreatureValues><CreatureValues><creatureType>Laczat</creatureType><evolutionType>None</evolutionType><damageType>Psychic</damageType><bodyType>Sand</bodyType><levelToEvolve>-1</levelToEvolve><evolution>2</evolution><damage>70</damage><speed>70</speed><defense>75</defense><magic>85</magic></CreatureValues><CreatureValues><creatureType>Spore</creatureType><evolutionType>Dreed</evolutionType><damageType>Plant</damageType><bodyType>Plant</bodyType><levelToEvolve>40</levelToEvolve><evolution>1</evolution><damage>75</damage><speed>75</speed><defense>80</defense><magic>70</magic></CreatureValues><CreatureValues><creatureType>Phypo</creatureType><evolutionType>None</evolutionType><damageType>Water</damageType><bodyType>Water</bodyType><levelToEvolve>-1</levelToEvolve><evolution>1</evolution><damage>71</damage><speed>71</speed><defense>71</defense><magic>71</magic></CreatureValues><CreatureValues><creatureType>Snock</creatureType><evolutionType>None</evolutionType><damageType>Sand</damageType><bodyType>Sand</bodyType><levelToEvolve>-1</levelToEvolve><evolution>1</evolution><damage>78</damage><speed>64</speed><defense>78</defense><magic>64</magic></CreatureValues><CreatureValues><creatureType>Clin</creatureType><evolutionType>None</evolutionType><damageType>Fire</damageType><bodyType>Fire</bodyType><levelToEvolve>-1</levelToEvolve><evolution>1</evolution><damage>78</damage><speed>64</speed><defense>64</defense><magic>78</magic></CreatureValues><CreatureValues><creatureType>Nymphae</creatureType><evolutionType>Nymph</evolutionType><damageType>Pet</damageType><bodyType>Plant</bodyType><levelToEvolve>40</levelToEvolve><evolution>1</evolution><damage>65</damage><speed>85</speed><defense>70</defense><magic>80</magic></CreatureValues><CreatureValues><creatureType>Choidal</creatureType><evolutionType>Chydaz</evolutionType><damageType>Pet</damageType><bodyType>Onyx</bodyType><levelToEvolve>40</levelToEvolve><evolution>1</evolution><damage>80</damage><speed>70</speed><defense>85</defense><magic>65</magic></CreatureValues><CreatureValues><creatureType>Chydaz</creatureType><evolutionType>Krathal</evolutionType><damageType>Ghost</damageType><bodyType>Onyx</bodyType><levelToEvolve>80</levelToEvolve><evolution>2</evolution><damage>80</damage><speed>70</speed><defense>85</defense><magic>65</magic></CreatureValues><CreatureValues><creatureType>Krathal</creatureType><evolutionType>None</evolutionType><damageType>Ghost</damageType><bodyType>Onyx</bodyType><levelToEvolve>-1</levelToEvolve><evolution>3</evolution><damage>80</damage><speed>70</speed><defense>85</defense><magic>65</magic></CreatureValues><CreatureValues><creatureType>Nymph</creatureType><evolutionType>None</evolutionType><damageType>Plant</damageType><bodyType>Psychic</bodyType><levelToEvolve>-1</levelToEvolve><evolution>2</evolution><damage>65</damage><speed>85</speed><defense>70</defense><magic>80</magic></CreatureValues><CreatureValues><creatureType>Croncat</creatureType><evolutionType>None</evolutionType><damageType>Psychic</damageType><bodyType>Pet</bodyType><levelToEvolve>-1</levelToEvolve><evolution>1</evolution><damage>75</damage><speed>84</speed><defense>70</defense><magic>87</magic></CreatureValues><CreatureValues><creatureType>Gobbler</creatureType><evolutionType>None</evolutionType><damageType>Sand</damageType><bodyType>Pet</bodyType><levelToEvolve>-1</levelToEvolve><evolution>1</evolution><damage>50</damage><speed>80</speed><defense>50</defense><magic>50</magic></CreatureValues><CreatureValues><creatureType>Strax</creatureType><evolutionType>Marark</evolutionType><damageType>Water</damageType><bodyType>Water</bodyType><levelToEvolve>80</levelToEvolve><evolution>2</evolution><damage>72</damage><speed>100</speed><defense>72</defense><magic>72</magic></CreatureValues><CreatureValues><creatureType>Marark</creatureType><evolutionType>None</evolutionType><damageType>Water</damageType><bodyType>Water</bodyType><levelToEvolve>-1</levelToEvolve><evolution>3</evolution><damage>72</damage><speed>100</speed><defense>72</defense><magic>72</magic></CreatureValues><CreatureValues><creatureType>Escheon</creatureType><evolutionType>None</evolutionType><damageType>Water</damageType><bodyType>Plant</bodyType><levelToEvolve>-1</levelToEvolve><evolution>2</evolution><damage>65</damage><speed>65</speed><defense>95</defense><magic>80</magic></CreatureValues><CreatureValues><creatureType>Hircus</creatureType><evolutionType>Hapran</evolutionType><damageType>Fire</damageType><bodyType>Pet</bodyType><levelToEvolve>40</levelToEvolve><evolution>1</evolution><damage>80</damage><speed>65</speed><defense>80</defense><magic>75</magic></CreatureValues><CreatureValues><creatureType>Hapran</creatureType><evolutionType>Gagrus</evolutionType><damageType>Fire</damageType><bodyType>Pet</bodyType><levelToEvolve>80</levelToEvolve><evolution>2</evolution><damage>80</damage><speed>65</speed><defense>80</defense><magic>75</magic></CreatureValues><CreatureValues><creatureType>Gagrus</creatureType><evolutionType>None</evolutionType><damageType>Fire</damageType><bodyType>Pet</bodyType><levelToEvolve>-1</levelToEvolve><evolution>3</evolution><damage>80</damage><speed>65</speed><defense>80</defense><magic>75</magic></CreatureValues><CreatureValues><creatureType>Bogy</creatureType><evolutionType>Fletch</evolutionType><damageType>Ghost</damageType><bodyType>Ghost</bodyType><levelToEvolve>40</levelToEvolve><evolution>1</evolution><damage>60</damage><speed>75</speed><defense>65</defense><magic>100</magic></CreatureValues><CreatureValues><creatureType>Fletch</creatureType><evolutionType>Shaitan</evolutionType><damageType>Ghost</damageType><bodyType>Ghost</bodyType><levelToEvolve>80</levelToEvolve><evolution>2</evolution><damage>60</damage><speed>75</speed><defense>65</defense><magic>100</magic></CreatureValues><CreatureValues><creatureType>Shaitan</creatureType><evolutionType>None</evolutionType><damageType>Ghost</damageType><bodyType>Ghost</bodyType><levelToEvolve>-1</levelToEvolve><evolution>3</evolution><damage>60</damage><speed>75</speed><defense>65</defense><magic>100</magic></CreatureValues><CreatureValues><creatureType>Achtea</creatureType><evolutionType>Pachaon</evolutionType><damageType>Plant</damageType><bodyType>Plant</bodyType><levelToEvolve>40</levelToEvolve><evolution>1</evolution><damage>80</damage><speed>85</speed><defense>85</defense><magic>50</magic></CreatureValues><CreatureValues><creatureType>Pachaon</creatureType><evolutionType>Aconthea</evolutionType><damageType>Plant</damageType><bodyType>Plant</bodyType><levelToEvolve>80</levelToEvolve><evolution>2</evolution><damage>80</damage><speed>85</speed><defense>85</defense><magic>50</magic></CreatureValues><CreatureValues><creatureType>Aconthea</creatureType><evolutionType>None</evolutionType><damageType>Plant</damageType><bodyType>Plant</bodyType><levelToEvolve>-1</levelToEvolve><evolution>3</evolution><damage>80</damage><speed>85</speed><defense>85</defense><magic>50</magic></CreatureValues><CreatureValues><creatureType>Simli</creatureType><evolutionType>Chordata</evolutionType><damageType>Water</damageType><bodyType>Fire</bodyType><levelToEvolve>40</levelToEvolve><evolution>1</evolution><damage>80</damage><speed>80</speed><defense>80</defense><magic>80</magic></CreatureValues><CreatureValues><creatureType>Chordata</creatureType><evolutionType>None</evolutionType><damageType>Water</damageType><bodyType>Fire</bodyType><levelToEvolve>-1</levelToEvolve><evolution>2</evolution><damage>80</damage><speed>80</speed><defense>80</defense><magic>80</magic></CreatureValues></ArrayOfCreatureValues>